<theme>

	<formatVersion>4</formatVersion>

	<view name="system">

		<text name="info1" extra="true">
			<text>Release Date: October 4, 1993</text>
		</text>

		<text name="info2" extra="true">
			<text>Developer: The 3DO Company</text>
		</text>

		<text name="info3" extra="true">
			<text>CPU: 32-bit RISC CPU ARM60</text>
		</text>

		<text name="info4" extra="true">
			<text>Memory: 2 MB RAM, 1 MB VRAM</text>
		</text>

		<text name="info5" extra="true">
			<text>Graphics: Panasonic FZ-1</text>
		</text>

		<text name="info6" extra="true">
			<text>Sound: 16-bit stereo sound</text>
		</text>

		<text name="info7" extra="true">
			<text>Media: CD-ROM</text>
		</text>

		<text name="info8" extra="true">
			<text>Best Selling Game: GEX</text>
		</text>

		<text name="info9" extra="true">
			<text>The 3DO was not a console manufactured by the company itself, but a</text>
		</text>

		<text name="info10" extra="true">
			<text>series of specifications that could be licensed by third parties.</text>

		</text>

		<text name="info11" extra="true">
			<text>Panasonic produced the first models in 1993.</text>
		</text>

	</view>


</theme>
